slidegeist/__init__.py
slidegeist/ai_description.py
slidegeist/cli.py
slidegeist/constants.py
slidegeist/download.py
slidegeist/export.py
slidegeist/ffmpeg.py
slidegeist/ffmpeg_scene.py
slidegeist/ocr.py
slidegeist/pipeline.py
slidegeist/pixel_diff_detector.py
slidegeist/slides.py
slidegeist/transcribe.py
slidegeist-2025.11.3.dist-info/METADATA
slidegeist-2025.11.3.dist-info/WHEEL
slidegeist-2025.11.3.dist-info/entry_points.txt
slidegeist-2025.11.3.dist-info/licenses/LICENSE
slidegeist-2025.11.3.dist-info/RECORD
