Metadata-Version: 2.4
Name: slidegeist
Version: 2025.11.3
Summary: Extract slides and transcripts from lecture videos with minimal dependencies
Author: Christopher Albert
License: MIT
License-File: LICENSE
Classifier: Development Status :: 3 - Alpha
Classifier: Intended Audience :: Education
Classifier: Intended Audience :: Science/Research
Classifier: License :: OSI Approved :: MIT License
Classifier: Programming Language :: Python :: 3
Classifier: Programming Language :: Python :: 3.10
Classifier: Programming Language :: Python :: 3.11
Classifier: Programming Language :: Python :: 3.12
Classifier: Topic :: Multimedia :: Video
Classifier: Topic :: Scientific/Engineering
Requires-Python: >=3.10
Requires-Dist: accelerate<2.0,>=0.20.0
Requires-Dist: bitsandbytes<1.0,>=0.40.0
Requires-Dist: numpy<3.0,>=2.2.0
Requires-Dist: openai-whisper>=20231117
Requires-Dist: opencv-python<5.0,>=4.10.0
Requires-Dist: pillow<12.0,>=11.0.0
Requires-Dist: psutil<8.0,>=7.0.0
Requires-Dist: pytesseract<1.0,>=0.3.13
Requires-Dist: torch<3.0,>=2.0.0
Requires-Dist: torchvision<1.0,>=0.15.0
Requires-Dist: tqdm<5.0,>=4.67.0
Requires-Dist: transformers<5.0,>=4.30.0
Requires-Dist: yt-dlp>=2024.12.0
Provides-Extra: dev
Requires-Dist: mypy>=1.0; extra == 'dev'
Requires-Dist: pytest-cov>=4.0; extra == 'dev'
Requires-Dist: pytest>=7.0; extra == 'dev'
Requires-Dist: ruff>=0.1.0; extra == 'dev'
Provides-Extra: mlx
Requires-Dist: mlx-whisper>=0.4.0; extra == 'mlx'
